{
  "default": {
    "access_token": "replicate-dimusdim:xPPlnuSUqSp9NI04:q5ueA3VGXVgXQi3wZnLcraPb22S14ewN",
    "token_type": "Bearer",
    "expires_in": 3600,
    "refresh_token": "replicate-dimusdim:xPPlnuSUqSp9NI04:gUp60l8LvekqyzYA3MwqZiiAMCJXUVw3",
    "scope": "read write"
  },
  "replicate": {
    "access_token": "replicate-dimusdim:OcRXSv52ajmKwaTl:r3tck2XAzQNWaEie8XQl0HF9bhMEP4Ox",
    "token_type": "Bearer",
    "expires_in": 3600,
    "refresh_token": "replicate-dimusdim:OcRXSv52ajmKwaTl:bAqyPMLpobhiKR7OkFCQGZCeMAqMyG5A",
    "scope": "read write"
  }
}